dlestxetx.py
dlestxetx-1.0.1.dist-info/LICENSE
dlestxetx-1.0.1.dist-info/METADATA
dlestxetx-1.0.1.dist-info/WHEEL
dlestxetx-1.0.1.dist-info/top_level.txt
dlestxetx-1.0.1.dist-info/RECORD
