Metadata-Version: 2.1
Name: dlestxetx
Version: 1.0.1
Summary: DLE/STX/ETX packet encoder/decoder
Home-page: https://github.com/Lx/python-dlestxetx
Author: Alex Peters
License: UNKNOWN
Keywords: DLE STX ETX
Platform: UNKNOWN
Classifier: Development Status :: 5 - Production/Stable
Classifier: License :: OSI Approved :: MIT License
Classifier: Natural Language :: English
Classifier: Operating System :: OS Independent
Classifier: Programming Language :: Python :: 3.5
Classifier: Programming Language :: Python :: 3.6
Classifier: Programming Language :: Python :: 3.7
Classifier: Topic :: Communications
Classifier: Typing :: Typed
Requires-Python: ~=3.5
